tts/__init__.py
tts/config.py
tts/download.py
tts/main.py
tts/make_file.py
tts/play.py
tts/errors/__init__.py
tts/errors/auth.py
tts/errors/files.py
tts/errors/shared.py
tts/utils/__init__.py
tts/utils/log.py
discord_tts_jp-1.0.0.dist-info/METADATA
discord_tts_jp-1.0.0.dist-info/WHEEL
discord_tts_jp-1.0.0.dist-info/top_level.txt
discord_tts_jp-1.0.0.dist-info/RECORD
