Metadata-Version: 2.2
Name: discord-tts-jp
Version: 1.0.0
Summary: discordの読み上げBOTに使用できるライブラリ(日本語only)
Requires-Python: >=3.13
Requires-Dist: discord-py
Requires-Dist: parameterized>=0.9.0
Requires-Dist: pytest>=8.3.4
